LICENSE.txt
MANIFEST.in
setup.py
pyWebBrowser/__init__.py
pyWebBrowser.egg-info/PKG-INFO
pyWebBrowser.egg-info/SOURCES.txt
pyWebBrowser.egg-info/dependency_links.txt
pyWebBrowser.egg-info/requires.txt
pyWebBrowser.egg-info/top_level.txt
pyWebBrowser/Browser/__init__.py
pyWebBrowser/MKC/__init__.py
pyWebBrowser/Win64Browser/CefSharp.BrowserSubprocess.Core.dll
pyWebBrowser/Win64Browser/CefSharp.BrowserSubprocess.Core.pdb
pyWebBrowser/Win64Browser/CefSharp.BrowserSubprocess.exe
pyWebBrowser/Win64Browser/CefSharp.BrowserSubprocess.pdb
pyWebBrowser/Win64Browser/CefSharp.Core.Runtime.dll
pyWebBrowser/Win64Browser/CefSharp.Core.Runtime.pdb
pyWebBrowser/Win64Browser/CefSharp.Core.Runtime.xml
pyWebBrowser/Win64Browser/CefSharp.Core.dll
pyWebBrowser/Win64Browser/CefSharp.Core.pdb
pyWebBrowser/Win64Browser/CefSharp.Core.xml
pyWebBrowser/Win64Browser/CefSharp.WinForms.dll
pyWebBrowser/Win64Browser/CefSharp.WinForms.pdb
pyWebBrowser/Win64Browser/CefSharp.WinForms.xml
pyWebBrowser/Win64Browser/CefSharp.dll
pyWebBrowser/Win64Browser/CefSharp.pdb
pyWebBrowser/Win64Browser/CefSharp.xml
pyWebBrowser/Win64Browser/LICENSE.txt
pyWebBrowser/Win64Browser/README.txt
pyWebBrowser/Win64Browser/Win64Browser.dll
pyWebBrowser/Win64Browser/Win64Browser.pdb
pyWebBrowser/Win64Browser/Win64Hook.dll
pyWebBrowser/Win64Browser/Win64Hook.pdb
pyWebBrowser/Win64Browser/Win64MKC.dll
pyWebBrowser/Win64Browser/Win64MKC.pdb
pyWebBrowser/Win64Browser/background.png
pyWebBrowser/Win64Browser/chrome_100_percent.pak
pyWebBrowser/Win64Browser/chrome_200_percent.pak
pyWebBrowser/Win64Browser/chrome_elf.dll
pyWebBrowser/Win64Browser/d3dcompiler_47.dll
pyWebBrowser/Win64Browser/icudtl.dat
pyWebBrowser/Win64Browser/index.html
pyWebBrowser/Win64Browser/libEGL.dll
pyWebBrowser/Win64Browser/libGLESv2.dll
pyWebBrowser/Win64Browser/libcef.dll
pyWebBrowser/Win64Browser/resources.pak
pyWebBrowser/Win64Browser/snapshot_blob.bin
pyWebBrowser/Win64Browser/v8_context_snapshot.bin
pyWebBrowser/Win64Browser/locales/am.pak
pyWebBrowser/Win64Browser/locales/ar.pak
pyWebBrowser/Win64Browser/locales/bg.pak
pyWebBrowser/Win64Browser/locales/bn.pak
pyWebBrowser/Win64Browser/locales/ca.pak
